{
  "announcement_id": "20250710_미지정",
  "title": "2025년도 서울지역 기존주택 매입 공고",
  "region": "미지정",
  "announcement_date": "2025-07-10",
  "application_start": "2025-07-10",
  "application_end": "2025-08-29",
  "min_units": 15,
  "max_exclusive_area": 85.0,
  "min_construction_start": "2009-01-01",
  "min_approval_date": "2015-01-01",
  "officetel_min_approval": "2010-01-01",
  "area_by_type": {
    "일반": {
      "min": 20,
      "max": 85
    },
    "청년": {
      "min": 16,
      "max": 60
    },
    "신혼신생아": {
      "min": 36,
      "max": 85
    },
    "다자녀": {
      "min": 46,
      "max": 85
    }
  },
  "exclusion_rules": [
    {
      "rule_id": "LOC_001",
      "category": "지리적_요건",
      "sub_category": "재정비촉진지구",
      "description": "「도시재정비 촉진을 위한 특별법」에 의한 재정비촉진지구 내 주택",
      "severity": "조건부",
      "check_field": "land_use_plan.is_redevelopment_zone",
      "check_condition": "== True",
      "exception_condition": "해제절차 진행 중이거나 존치관리구역으로 지정된 경우",
      "exception_documents": [
        "지구해제 합의서",
        "존치관리구역 지정 확인서"
      ],
      "legal_basis": "도시재정비 촉진을 위한 특별법",
      "reference_page": 4,
      "is_active": true
    },
    {
      "rule_id": "LOC_002",
      "category": "지리적_요건",
      "sub_category": "정비구역",
      "description": "「도시 및 주거환경정비법」에 의한 정비구역 내 주택",
      "severity": "조건부",
      "check_field": "land_use_plan.is_maintenance_zone",
      "check_condition": "== True",
      "exception_condition": "현지개량방식의 주거환경개선사업계획이 확정/준공된 경우",
      "exception_documents": [
        "주거환경개선사업 확정/준공 확인서"
      ],
      "legal_basis": "도시 및 주거환경정비법",
      "reference_page": 4,
      "is_active": true
    },
    {
      "rule_id": "LOC_003",
      "category": "지리적_요건",
      "sub_category": "공공주택지구",
      "description": "「공공주택 특별법」에 의한 공공주택지구 및 도심공공주택복합지구(후보지 포함) 내 주택",
      "severity": "절대_제외",
      "check_field": "land_use_plan.is_public_housing_zone",
      "check_condition": "== True",
      "exception_condition": null,
      "exception_documents": [],
      "legal_basis": "공공주택 특별법",
      "reference_page": 4,
      "is_active": true
    },
    {
      "rule_id": "LOC_004",
      "category": "지리적_요건",
      "sub_category": "택지개발예정지구",
      "description": "「택지개발촉진법」에 의한 택지개발예정지구 내 주택",
      "severity": "절대_제외",
      "check_field": "land_use_plan.is_housing_development_zone",
      "check_condition": "== True",
      "exception_condition": null,
      "exception_documents": [],
      "legal_basis": "택지개발촉진법",
      "reference_page": 4,
      "is_active": true
    },
    {
      "rule_id": "LOC_005",
      "category": "지리적_요건",
      "sub_category": "소규모주택정비사업구역",
      "description": "「빈집 및 소규모주택 정비에 관한 특례법」에 따른 사업시행구역 내 주택",
      "severity": "절대_제외",
      "check_field": "land_use_plan.is_small_housing_redevelopment_zone",
      "check_condition": "== True",
      "exception_condition": null,
      "exception_documents": [],
      "legal_basis": "빈집 및 소규모주택 정비에 관한 특례법",
      "reference_page": 4,
      "is_active": true
    },
    {
      "rule_id": "LOC_006",
      "category": "지리적_요건",
      "sub_category": "도시가스_미설치",
      "description": "도시가스 미설치 지역의 주택",
      "severity": "조건부",
      "check_field": "utilities.has_city_gas",
      "check_condition": "== False",
      "exception_condition": "농어촌 등 지역여건상 설치 불가능 지역이거나 매도자가 설치하여 문제없는 경우",
      "exception_documents": [],
      "legal_basis": null,
      "reference_page": 4,
      "is_active": true
    },
    {
      "rule_id": "LOC_007",
      "category": "지리적_요건",
      "sub_category": "상하수도_미설치",
      "description": "상하수도 미설치 지역의 주택",
      "severity": "조건부",
      "check_field": "utilities.has_water_sewage",
      "check_condition": "== False",
      "exception_condition": "농어촌 등 지역여건상 설치 불가능 지역이거나 매도자가 설치하여 문제없는 경우",
      "exception_documents": [],
      "legal_basis": null,
      "reference_page": 4,
      "is_active": true
    },
    {
      "rule_id": "LOC_008",
      "category": "지리적_요건",
      "sub_category": "군부대_화장장_인접",
      "description": "직선거리 500m 이내 군부대 사격장·화장장이 있는 지역의 주택",
      "severity": "절대_제외",
      "check_field": "location.near_military_or_crematorium_500m",
      "check_condition": "== True",
      "exception_condition": null,
      "exception_documents": [],
      "legal_basis": null,
      "reference_page": 5,
      "is_active": true
    },
    {
      "rule_id": "LOC_009",
      "category": "지리적_요건",
      "sub_category": "유해시설_50m",
      "description": "직선거리 50m 이내「주택건설기준 등에 관한 규정」제9조의2 제1항 제1호 및 제2호 시설이 있는 주택",
      "severity": "조건부",
      "check_field": "location.near_harmful_facility_50m",
      "check_condition": "== True",
      "exception_condition": "주거용 오피스텔은 해당 기준 미적용",
      "exception_documents": [],
      "legal_basis": null,
      "reference_page": 5,
      "is_active": true
    },
    {
      "rule_id": "LOC_010",
      "category": "지리적_요건",
      "sub_category": "주유소_25m",
      "description": "직선거리 25m 이내 주유소·석유판매취급소·자동차용 천연가스충전소가 있는 주택",
      "severity": "절대_제외",
      "check_field": "location.near_gas_station_25m",
      "check_condition": "== True",
      "exception_condition": null,
      "exception_documents": [],
      "legal_basis": null,
      "reference_page": 5,
      "is_active": true
    },
    {
      "rule_id": "LOC_011",
      "category": "지리적_요건",
      "sub_category": "숙박위락시설_25m_다자녀",
      "description": "직선거리 25m 이내 일반숙박시설·위락시설이 있는 다자녀 유형 주택",
      "severity": "절대_제외",
      "check_field": "location.near_entertainment_25m",
      "check_condition": "== True and housing_type == '다자녀'",
      "exception_condition": null,
      "exception_documents": [],
      "legal_basis": null,
      "reference_page": 5,
      "is_active": true
    },
    {
      "rule_id": "LOC_012",
      "category": "지리적_요건",
      "sub_category": "맹지",
      "description": "맹지 상태 또는 타인 소유의 시설물에 의해 부속토지가 점유된 주택",
      "severity": "조건부",
      "check_field": "land.is_landlocked",
      "check_condition": "== True",
      "exception_condition": "점유해소 가능한 객관적 증빙자료 제출 시 조건부 신청 가능",
      "exception_documents": [
        "점유해소 증빙자료"
      ],
      "legal_basis": null,
      "reference_page": 5,
      "is_active": true
    },
    {
      "rule_id": "LOC_013",
      "category": "지리적_요건",
      "sub_category": "진입도로_미확보",
      "description": "주택 진입도로가 미확보된 주택 (출입로가 사도인 경우 등)",
      "severity": "조건부",
      "check_field": "land.has_access_road",
      "check_condition": "== False",
      "exception_condition": "진입도로가 사도인 경우 LH에 무상귀속 또는 지자체에 기부채납 조건, 또는 지역권 설정 계약 및 등기된 경우",
      "exception_documents": [
        "무상귀속 확인서",
        "기부채납 확인서",
        "지역권 설정계약서"
      ],
      "legal_basis": null,
      "reference_page": 5,
      "is_active": true
    },
    {
      "rule_id": "HSG_001",
      "category": "주택_요건",
      "sub_category": "지하세대",
      "description": "지하(반지하 포함) 세대가 있는 주택",
      "severity": "절대_제외",
      "check_field": "building.has_basement_units",
      "check_condition": "== True",
      "exception_condition": null,
      "exception_documents": [],
      "legal_basis": null,
      "reference_page": 6,
      "is_active": true
    },
    {
      "rule_id": "HSG_002",
      "category": "주택_요건",
      "sub_category": "최저주거기준_미달",
      "description": "국토교통부 공고「최저주거기준」에 미달하는 주택",
      "severity": "절대_제외",
      "check_field": "building.meets_minimum_housing_standard",
      "check_condition": "== False",
      "exception_condition": null,
      "exception_documents": [],
      "legal_basis": "국토교통부 최저주거기준",
      "reference_page": 6,
      "is_active": true
    },
    {
      "rule_id": "HSG_003",
      "category": "주택_요건",
      "sub_category": "불법건축물",
      "description": "불법 건축물 및 법률상 제한사유(건축법 위반, 압류 및 가압류, 경매개시 등)가 있는 주택",
      "severity": "조건부",
      "check_field": "building.is_illegal_construction",
      "check_condition": "== True",
      "exception_condition": "불법건축물을 치유하여 구조상 문제가 없는 경우, 법률상 제한사유 해소 가능한 경우 조건부 신청 가능",
      "exception_documents": [],
      "legal_basis": null,
      "reference_page": 6,
      "is_active": true
    },
    {
      "rule_id": "HSG_004",
      "category": "주택_요건",
      "sub_category": "압류_가압류",
      "description": "압류 및 가압류가 있는 주택",
      "severity": "조건부",
      "check_field": "registry.has_seizure",
      "check_condition": "== True",
      "exception_condition": "법률상 제한사유 해소 가능한 경우 조건부 신청 가능",
      "exception_documents": [],
      "legal_basis": null,
      "reference_page": 6,
      "is_active": true
    },
    {
      "rule_id": "HSG_005",
      "category": "주택_요건",
      "sub_category": "경매개시",
      "description": "경매개시 결정이 있는 주택",
      "severity": "조건부",
      "check_field": "registry.has_auction",
      "check_condition": "== True",
      "exception_condition": "법률상 제한사유 해소 가능한 경우 조건부 신청 가능",
      "exception_documents": [],
      "legal_basis": null,
      "reference_page": 6,
      "is_active": true
    },
    {
      "rule_id": "HSG_006",
      "category": "주택_요건",
      "sub_category": "외벽마감재_부적합_신규",
      "description": "건축허가일이 2019.11.7일 이후인 경우 외벽 마감재료가 준불연재 또는 불연재 성능을 만족하지 않는 주택",
      "severity": "절대_제외",
      "check_field": "building.exterior_material_compliant",
      "check_condition": "== False and permit_date >= '2019-11-07'",
      "exception_condition": null,
      "exception_documents": [
        "외벽 단열재 시험성적서",
        "납품확인서",
        "시공사진"
      ],
      "legal_basis": null,
      "reference_page": 6,
      "is_active": true
    },
    {
      "rule_id": "HSG_007",
      "category": "주택_요건",
      "sub_category": "외벽마감재_부적합_기존",
      "description": "건축허가일이 2019.11.6일 이전인 경우 외벽 단열재 또는 마감재가 준불연재 성능 이상을 만족하지 않는 주택",
      "severity": "절대_제외",
      "check_field": "building.exterior_material_compliant",
      "check_condition": "== False and permit_date < '2019-11-07'",
      "exception_condition": null,
      "exception_documents": [
        "외벽 단열재/마감재 시험성적서"
      ],
      "legal_basis": null,
      "reference_page": 6,
      "is_active": true
    },
    {
      "rule_id": "HSG_008",
      "category": "주택_요건",
      "sub_category": "내진설계_미반영",
      "description": "관련법령(건축법 등)에 따른 내진설계가 반영되지 않은 주택",
      "severity": "절대_제외",
      "check_field": "building.has_seismic_design",
      "check_condition": "== False",
      "exception_condition": "내진설계 기준은 건축허가 시점의 적용기준을 따름",
      "exception_documents": [],
      "legal_basis": "건축법",
      "reference_page": 6,
      "is_active": true
    },
    {
      "rule_id": "HSG_009",
      "category": "주택_요건",
      "sub_category": "계량기_미설치",
      "description": "세대별 전기 및 수도계량기가 설치되지 않은 주택",
      "severity": "조건부",
      "check_field": "building.has_individual_meters",
      "check_condition": "== False",
      "exception_condition": "계량기 추가설치가 가능한 경우 조건부 신청 가능",
      "exception_documents": [],
      "legal_basis": null,
      "reference_page": 6,
      "is_active": true
    },
    {
      "rule_id": "HSG_010",
      "category": "주택_요건",
      "sub_category": "주거공간_미확보",
      "description": "세대 내 보일러실 및 세탁기, 냉장고 및 조리공간 확보가 어려운 주택",
      "severity": "절대_제외",
      "check_field": "building.has_adequate_living_space",
      "check_condition": "== False",
      "exception_condition": null,
      "exception_documents": [],
      "legal_basis": null,
      "reference_page": 6,
      "is_active": true
    },
    {
      "rule_id": "HSG_011",
      "category": "주택_요건",
      "sub_category": "승강기_미설치",
      "description": "승강기 미설치 주택",
      "severity": "절대_제외",
      "check_field": "building.has_elevator",
      "check_condition": "== False",
      "exception_condition": null,
      "exception_documents": [],
      "legal_basis": null,
      "reference_page": 6,
      "is_active": true
    },
    {
      "rule_id": "HSG_012",
      "category": "주택_요건",
      "sub_category": "욕실배관_매립",
      "description": "욕실 천장 오·배수관이 콘크리트에 매립된 주택",
      "severity": "절대_제외",
      "check_field": "building.bathroom_pipes_embedded",
      "check_condition": "== True",
      "exception_condition": null,
      "exception_documents": [],
      "legal_basis": null,
      "reference_page": 6,
      "is_active": true
    },
    {
      "rule_id": "OTH_001",
      "category": "기타_요건",
      "sub_category": "권리관계_미해소",
      "description": "주택의 잔여지분이 존재하거나, 부동산 권리관계가 해소되지 않은 등 법률적 또는 사실적 분쟁이 있는 주택",
      "severity": "절대_제외",
      "check_field": "ownership.has_unresolved_rights",
      "check_condition": "== True",
      "exception_condition": null,
      "exception_documents": [],
      "legal_basis": null,
      "reference_page": 6,
      "is_active": true
    },
    {
      "rule_id": "OTH_002",
      "category": "기타_요건",
      "sub_category": "LH직원_가족",
      "description": "매도신청인 본인 및 직계 존·비속, 배우자 및 배우자의 직계 존·비속이 前·現 공사 직원인 경우",
      "severity": "절대_제외",
      "check_field": "applicant.is_lh_employee_or_family",
      "check_condition": "== True",
      "exception_condition": "퇴직직원의 경우 퇴직일로부터 5년간 적용",
      "exception_documents": [],
      "legal_basis": null,
      "reference_page": 6,
      "is_active": true
    },
    {
      "rule_id": "OTH_003",
      "category": "기타_요건",
      "sub_category": "부정행위_제재자",
      "description": "청탁 등 부정한 행위로 공사로부터 제재를 받은 행위자가 소유(중개)하는 주택",
      "severity": "절대_제외",
      "check_field": "applicant.has_fraud_sanction",
      "check_condition": "== True",
      "exception_condition": null,
      "exception_documents": [],
      "legal_basis": null,
      "reference_page": 7,
      "is_active": true
    },
    {
      "rule_id": "OTH_004",
      "category": "기타_요건",
      "sub_category": "재신청_제한",
      "description": "공사에서 2회 이상 매입대상 제외한 주택으로 매입 제외 사유를 해소하지 않고 재신청한 주택",
      "severity": "조건부",
      "check_field": "history.exclusion_count",
      "check_condition": ">= 2",
      "exception_condition": "매입 제외 사유를 해소한 경우 신청 가능",
      "exception_documents": [],
      "legal_basis": null,
      "reference_page": 7,
      "is_active": true
    },
    {
      "rule_id": "OTH_005",
      "category": "기타_요건",
      "sub_category": "미분양_아파트",
      "description": "미분양 아파트에 해당하는 주택",
      "severity": "조건부",
      "check_field": "building.is_unsold_apartment",
      "check_condition": "== True",
      "exception_condition": "도시형생활주택 아파트는 매입 가능",
      "exception_documents": [],
      "legal_basis": null,
      "reference_page": 7,
      "is_active": true
    },
    {
      "rule_id": "OTH_006",
      "category": "기타_요건",
      "sub_category": "전세사기피해_주택",
      "description": "「전세사기 피해자 지원 및 주거안정에 관한 특별법」에 따른 전세사기피해 주택",
      "severity": "절대_제외",
      "check_field": "building.is_jeonse_fraud_housing",
      "check_condition": "== True",
      "exception_condition": null,
      "exception_documents": [],
      "legal_basis": "전세사기 피해자 지원 및 주거안정에 관한 특별법",
      "reference_page": 7,
      "is_active": true
    }
  ],
  "created_at": "2026-02-02T17:18:04.068431",
  "updated_at": "2026-02-02T17:18:04.068661",
  "source_file": ""
}